pyparams/__init__.py
pyparams-0.3.0.dist-info/DESCRIPTION.rst
pyparams-0.3.0.dist-info/METADATA
pyparams-0.3.0.dist-info/RECORD
pyparams-0.3.0.dist-info/WHEEL
pyparams-0.3.0.dist-info/metadata.json
pyparams-0.3.0.dist-info/top_level.txt
