Metadata-Version: 2.0
Name: pyparams
Version: 0.3.0
Summary: Simple, powerfule program parameter processing.
Home-page: https://github.com/jbrendel/pyparams
Author: Juergen Brendel
Author-email: juergen@brendel.com
License: Apache
Keywords: python,command line,parameters,environment,config file
Platform: UNKNOWN
Classifier: License :: OSI Approved :: Apache Software License
Classifier: Intended Audience :: Developers
Classifier: Programming Language :: Python
